p3orm/__init__.py
p3orm/core.py
p3orm/drivers/__init__.py
p3orm/drivers/base.py
p3orm/drivers/postgres.py
p3orm/drivers/sqlite.py
p3orm/exceptions.py
p3orm/fields.py
p3orm/py.typed
p3orm/table.py
p3orm/types.py
p3orm/utils.py
p3orm-0.10.3.dist-info/LICENSE
p3orm-0.10.3.dist-info/METADATA
p3orm-0.10.3.dist-info/WHEEL
p3orm-0.10.3.dist-info/RECORD
