Metadata-Version: 2.1
Name: p3orm
Version: 0.10.3
Summary: Utilitarian Python ORM for Postgres/SQLite, backed by asyncpg/aiosqlite, Pydantic, and PyPika
Home-page: https://rafalstapinski.github.io/p3orm
License: MIT
Keywords: postgres,sqlite,async,orm
Author: Rafal Stapinski
Author-email: stapinskirafal@gmail.com
Requires-Python: >=3.9,<4.0
Classifier: License :: OSI Approved :: MIT License
Classifier: Programming Language :: Python :: 3
Classifier: Programming Language :: Python :: 3.9
Classifier: Programming Language :: Python :: 3.10
Classifier: Programming Language :: Python :: 3.11
Classifier: Programming Language :: Python :: 3.12
Provides-Extra: postgres
Provides-Extra: sqlite
Requires-Dist: PyPika (>=0.48.8,<0.49.0)
Requires-Dist: aiosqlite (>=0.17.0,<0.18.0) ; extra == "sqlite"
Requires-Dist: asyncpg (>=0.26.0,<0.27.0) ; extra == "postgres"
Requires-Dist: pydantic (>=2.3.0,<3.0.0)
Requires-Dist: typing-extensions (>=4.8.0,<5.0.0)
Project-URL: Repository, https://github.com/rafalstapinski/p3orm
